gitaid/__init__.py
gitaid/__main__.py
gitaid/logs.py
gitaid/test_azure.py
gitaid/test_openai.py
gitaid/test_vllm.py
gitaid/commands/__init__.py
gitaid/commands/commit.py
gitaid/commands/explain.py
gitaid/commands/setup.py
gitaid/core/__init__.py
gitaid/core/llm.py
gitaid/providers/__init__.py
gitaid/providers/azure.py
gitaid/providers/openai.py
gitaid/providers/vllm.py
gitaid/utils/__init__.py
gitaid/utils/config.py
gitaid/utils/validators.py
gitaid-0.2.9.dist-info/licenses/LICENSE.txt
gitaid-0.2.9.dist-info/METADATA
gitaid-0.2.9.dist-info/WHEEL
gitaid-0.2.9.dist-info/entry_points.txt
gitaid-0.2.9.dist-info/top_level.txt
gitaid-0.2.9.dist-info/RECORD
