Metadata-Version: 2.4
Name: gitaid
Version: 0.2.9
Summary: AI-powered aid for Git
Author-email: Athira <athira.srivani@gmail.com>
License: Apache-2.0
Requires-Python: >=3.9
License-File: LICENSE.txt
Requires-Dist: click
Requires-Dist: openai
Requires-Dist: keyring
Requires-Dist: pyyaml
Requires-Dist: loguru
Requires-Dist: vllm
Dynamic: license-file
